wordstop.py
wordstop-0.0.2.dist-info/DESCRIPTION.rst
wordstop-0.0.2.dist-info/METADATA
wordstop-0.0.2.dist-info/RECORD
wordstop-0.0.2.dist-info/WHEEL
wordstop-0.0.2.dist-info/entry_points.txt
wordstop-0.0.2.dist-info/metadata.json
wordstop-0.0.2.dist-info/top_level.txt
