Metadata-Version: 2.0
Name: wordstop
Version: 0.0.2
Summary: Word frequency counter
Home-page: https://github.com/hvnsweeting/wordstop
Author: Viet Hung Nguyen
Author-email: hvn@familug.org
License: UNKNOWN
Platform: UNKNOWN
Requires-Dist: nltk
